LICENSE
MANIFEST.in
README.md
requirements.txt
setup.py
pyauto/__init__.py
pyauto.csvdb.egg-info/PKG-INFO
pyauto.csvdb.egg-info/SOURCES.txt
pyauto.csvdb.egg-info/dependency_links.txt
pyauto.csvdb.egg-info/requires.txt
pyauto.csvdb.egg-info/top_level.txt
pyauto/csvdb/__init__.py
pyauto/csvdb/commands.py
pyauto/csvdb/config.py
pyauto/csvdb/db.py