Metadata-Version: 1.0
Name: pyauto.csvdb
Version: 0.0.1a1
Summary: Tools for converting a CSV into a database
Home-page: https://github.com/adamjaso/pyauto/tree/master/csvdb
Author: Adam Jaso
Author-email: UNKNOWN
License: GNU General Public License V2
Platform: UNKNOWN
